ai/__init__.py
ai/ai_client.py
ai/ai_client_config.py
ai/ai_client_factory.py
ai/aws/__init__.py
ai/aws/bedrock_client.py
ai/aws/bedrock_client_config.py
ai/aws/anthropic/__init__.py
ai/aws/anthropic/claude_client.py
ai/aws/anthropic/claude_client_config.py
ai/openai/__init__.py
ai/openai/openai_client.py
ai/openai/openai_config.py
cli/__init__.py
cli/app.py
cli/app_factory.py
cli/code_app.py
cli/file_app.py
cli/process_app.py
cli/prompt_app.py
cli/url_app.py
crowler-0.0.4.dist-info/licenses/LICENSE
db/__init__.py
db/file_history_db.py
db/history_db.py
db/process_file_db.py
db/prompt_db.py
db/shared_file_db.py
db/url_db.py
instruction/__init__.py
instruction/instruction_model.py
instruction/instructions/__init__.py
instruction/instructions/instruction_review.py
instruction/instructions/mypy.py
instruction/instructions/readme.py
instruction/instructions/response_format.py
instruction/instructions/typer_log.py
instruction/instructions/unit_test.py
util/__init__.py
util/ai_util.py
util/file_util.py
util/html_util.py
util/session_util.py
util/string_util.py
crowler-0.0.4.dist-info/METADATA
crowler-0.0.4.dist-info/WHEEL
crowler-0.0.4.dist-info/entry_points.txt
crowler-0.0.4.dist-info/top_level.txt
crowler-0.0.4.dist-info/RECORD
